ImmuneBuilder/ABodyBuilder2.py
ImmuneBuilder/NanoBodyBuilder2.py
ImmuneBuilder/TCRBuilder2.py
ImmuneBuilder/__init__.py
ImmuneBuilder/constants.py
ImmuneBuilder/models.py
ImmuneBuilder/refine.py
ImmuneBuilder/rigids.py
ImmuneBuilder/sequence_checks.py
ImmuneBuilder/util.py
ImmuneBuilder/trained_model/.gitkeep
ImmuneBuilder/trained_model/antibody_model_1
ImmuneBuilder/trained_model/antibody_model_2
ImmuneBuilder/trained_model/antibody_model_3
ImmuneBuilder/trained_model/antibody_model_4
ImmuneBuilder/trained_model/nanobody_model_1
ImmuneBuilder/trained_model/nanobody_model_2
ImmuneBuilder/trained_model/nanobody_model_3
ImmuneBuilder/trained_model/nanobody_model_4
ImmuneBuilder/trained_model/tcr2_model_1
ImmuneBuilder/trained_model/tcr2_model_2
ImmuneBuilder/trained_model/tcr2_model_3
ImmuneBuilder/trained_model/tcr2_model_4
ImmuneBuilder/trained_model/tcr_model_1
ImmuneBuilder/trained_model/tcr_model_2
ImmuneBuilder/trained_model/tcr_model_3
ImmuneBuilder/trained_model/tcr_model_4
ImmuneBuilder-1.2.dist-info/LICENSE
ImmuneBuilder-1.2.dist-info/METADATA
ImmuneBuilder-1.2.dist-info/WHEEL
ImmuneBuilder-1.2.dist-info/entry_points.txt
ImmuneBuilder-1.2.dist-info/top_level.txt
ImmuneBuilder-1.2.dist-info/RECORD
