Metadata-Version: 2.1
Name: ImmuneBuilder
Version: 1.2
Summary: Set of functions to predict the structure of immune receptor proteins
Maintainer: Brennan Abanades
Maintainer-email: brennan.abanadeskenyon@stx.ox.ac.uk
License: BSD 3-clause license
License-File: LICENSE
Requires-Dist: numpy
Requires-Dist: scipy >=1.6
Requires-Dist: einops >=0.3
Requires-Dist: torch >=1.8
Requires-Dist: requests
